iTunesContactsExport/__init__.py
iTunesContactsExport/__main__.py
iTunesContactsExport/iTunesDatabase/__init.py__
iTunesContactsExport/iTunesDatabase/iPhoneAddressBookDAO.py
iTunesContactsExport/iTunesDatabase/iPhoneAddressBookImagesDAO.py
iTunesContactsExport/iTunesDatabase/iPhoneManifestDAO.py
iTunesContactsExport/vCard/vCardBuilder.py
itunescontactsexport-0.1.1.dist-info/entry_points.txt
itunescontactsexport-0.1.1.dist-info/LICENSE
itunescontactsexport-0.1.1.dist-info/WHEEL
itunescontactsexport-0.1.1.dist-info/METADATA
itunescontactsexport-0.1.1.dist-info/RECORD
