Metadata-Version: 2.1
Name: itunescontactsexport
Version: 0.1.1
Summary: This small program will export your contact from an itunes backup.
Home-page: https://github.com/Tinigriffy/iTunesContactsExport
License: Apache-2.0
Keywords: itunes,iPhone,ipad,vcard,export
Author: Tinigriffy
Author-email: beistin@gmail.com
Requires-Python: >=3.9,<4.0
Classifier: License :: OSI Approved :: Apache Software License
Classifier: Operating System :: OS Independent
Classifier: Programming Language :: Python :: 3
Classifier: Programming Language :: Python :: 3.10
Classifier: Programming Language :: Python :: 3.9
Requires-Dist: vobject (>=0.9.6.1,<0.10.0.0)
Project-URL: Repository, https://github.com/Tinigriffy/iTunesContactsExport
